brworkittools/__init__.py
brworkittools/dock/__init__.py
brworkittools/dock/database_service.py
brworkittools/dock/s3_service.py
brworkittools/dock/secrets_manager_service.py
brworkittools/dock/ses_service.py
brworkittools/dock/slack_service.py
brworkittools/dock/sqs_service.py
brworkittools/dock/webhook_service.py
brworkittools/dock/zendesk_service.py
brworkittools/utils/__init__.py
brworkittools/utils/email_validator.py
brworkittools/utils/ssh_validator.py
tests/__init__.py
tests/dock_test.py
brworkittools-0.0.6.dist-info/LICENSE
brworkittools-0.0.6.dist-info/METADATA
brworkittools-0.0.6.dist-info/WHEEL
brworkittools-0.0.6.dist-info/top_level.txt
brworkittools-0.0.6.dist-info/RECORD
