Metadata-Version: 2.1
Name: brworkittools
Version: 0.0.6
Summary: A python package for avoid repetitions
Home-page: https://github.com/brworkit/brworkit-tools.git
Author: brworkit
Author-email: brworkit@gmail.com
License: UNKNOWN
Platform: UNKNOWN
Classifier: Programming Language :: Python :: 3
Classifier: License :: OSI Approved :: MIT License
Classifier: Operating System :: OS Independent
Requires-Python: >=3.6
